{
    "prepare_queue": {
        "installed": [],
        "uninstalled": []
    },
    "config_munge": {
        "files": {}
    },
    "installed_plugins": {
        "cordova-plugin-console": {
            "PACKAGE_NAME": "io.cordova.myapp89640b"
        },
        "cordova-plugin-file": {
            "PACKAGE_NAME": "io.cordova.myapp89640b"
        },
        "cordova-plugin-geolocation": {
            "PACKAGE_NAME": "io.cordova.myapp89640b"
        },
        "cordova-plugin-whitelist": {
            "PACKAGE_NAME": "io.cordova.myapp89640b"
        }
    },
    "dependent_plugins": {}
}